cpc.geoplot-0.1.18-py3.7-nspkg.pth
cpc/geoplot/__init__.py
cpc/geoplot/colors.py
cpc/geoplot/exceptions.py
cpc/geoplot/geofield.py
cpc/geoplot/geomap.py
cpc/geoplot/midpoint_norm.py
cpc/geoplot/test.py
cpc/geoplot/data/states.dbf
cpc/geoplot/data/states.shp
cpc/geoplot/data/states.shx
cpc/geoplot/images/empty-Geomap-equal-area-CONUS.png
cpc/geoplot/images/empty-Geomap-equal-area-NA.png
cpc/geoplot/images/empty-Geomap-equal-area-US.png
cpc/geoplot/images/empty-Geomap-lcc-CONUS.png
cpc/geoplot/images/empty-Geomap-lcc-NA.png
cpc/geoplot/images/empty-Geomap-lcc-US.png
cpc/geoplot/images/empty-Geomap-mercator-CONUS.png
cpc/geoplot/images/empty-Geomap-mercator-NA.png
cpc/geoplot/images/empty-Geomap-mercator-US.png
cpc/geoplot/images/empty-Geomap-mercator-global.png
cpc.geoplot-0.1.18.dist-info/AUTHORS.md
cpc.geoplot-0.1.18.dist-info/LICENSE.md
cpc.geoplot-0.1.18.dist-info/METADATA
cpc.geoplot-0.1.18.dist-info/WHEEL
cpc.geoplot-0.1.18.dist-info/namespace_packages.txt
cpc.geoplot-0.1.18.dist-info/top_level.txt
cpc.geoplot-0.1.18.dist-info/RECORD
