Metadata-Version: 2.1
Name: cpc.geoplot
Version: 0.1.18
Summary: CPC geospatial plotting
Home-page: https://github.com/noaa-nws-cpc/cpc.geoplot
Author: Mike Charles
Author-email: mike.charles@noaa.gov
License: CC
Platform: UNKNOWN
Classifier: Development Status :: 1 - Planning
Classifier: Environment :: Console
Classifier: Intended Audience :: Science/Research
Classifier: Programming Language :: Python
Classifier: Programming Language :: Python :: 3
Classifier: Operating System :: OS Independent
Classifier: Topic :: Scientific/Engineering :: Atmospheric Science
Classifier: License :: CC0 1.0 Universal (CC0 1.0) Public Domain Dedication
Requires-Dist: pyyaml
Requires-Dist: numpy
Requires-Dist: scipy
Requires-Dist: basemap
Requires-Dist: matplotlib
Requires-Dist: cpc.geogrids
